{"0": {"pTree": {"c": [{"c": [{"c": [], "d": {"t": 4, "v": "2.0.0"}, "n": "VERSION"}], "d": {}, "n": "Visible"}], "d": {}, "n": "window"}, "version": "2.0.0", "Sm": [], "version_list": ["2.0.0"]}, "1": {"pTree": {"c": [{"c": [{"c": [], "d": {"t": 6}, "n": "_hasClass"}], "d": {}, "n": "Visible"}], "d": {}, "n": "window"}, "version": "2.0.0-rc.1", "Sm": [0], "version_list": ["2.0.0-rc.1"]}, "2": {"pTree": {"c": [{"c": [{"c": [], "d": {"t": 4, "v": "2.1.0"}, "n": "VERSION"}], "d": {}, "n": "Visible"}], "d": {}, "n": "window"}, "version": "2.1.0", "Sm": [], "version_list": ["2.1.0"]}, "3": {"pTree": {"c": [{"c": [{"c": [], "d": {"t": 4, "v": "2.1.1"}, "n": "VERSION"}], "d": {}, "n": "Visible"}], "d": {}, "n": "window"}, "version": "2.1.1", "Sm": [], "version_list": ["2.1.1"]}, "4": {"pTree": {"c": [{"c": [{"c": [], "d": {"t": 4, "v": "2.2.0"}, "n": "VERSION"}], "d": {}, "n": "Visible"}], "d": {}, "n": "window"}, "version": "2.2.0", "Sm": [], "version_list": ["2.2.0"]}, "5": {"pTree": {"c": [{"c": [{"c": [], "d": {"t": 4, "v": "2.3.0"}, "n": "VERSION"}], "d": {}, "n": "Visible"}], "d": {}, "n": "window"}, "version": "2.3.0", "Sm": [], "version_list": ["2.3.0"]}, "6": {"pTree": {"c": [{"c": [{"c": [], "d": {"t": 4, "v": "2.3.0-beta.0"}, "n": "VERSION"}], "d": {}, "n": "Visible"}], "d": {}, "n": "window"}, "version": "2.3.0-beta.0", "Sm": [], "version_list": ["2.3.0-beta.0"]}, "7": {"pTree": {"c": [{"c": [{"c": [], "d": {"t": 4, "v": "2.4.0"}, "n": "VERSION"}], "d": {}, "n": "Visible"}], "d": {}, "n": "window"}, "version": "2.4.0", "Sm": [], "version_list": ["2.4.0"]}}